cocotbext/waves/__init__.py
cocotbext/waves/version.py
cocotbext/waves/waves.py
cocotbext_waves-0.1.9.dist-info/LICENSE
cocotbext_waves-0.1.9.dist-info/METADATA
cocotbext_waves-0.1.9.dist-info/WHEEL
cocotbext_waves-0.1.9.dist-info/top_level.txt
cocotbext_waves-0.1.9.dist-info/RECORD
