Metadata-Version: 2.1
Name: cocotbext-waves
Version: 0.1.9
Summary: CocotbExt Wavedrom diagram generator
Home-page: https://github.com/aignacio/cocotbext-waves
Author: aignacio (Anderson Ignacio)
Author-email: <anderson@aignacio.com>
License: MIT
Project-URL: Bug Tracker, https://github.com/aignacio/cocotbext-waves/issues
Project-URL: Source Code, https://github.com/aignacio/cocotbext-waves
Keywords: soc,vip,hdl,verilog,systemverilog,wavedrom
Classifier: Development Status :: 3 - Alpha
Classifier: Framework :: cocotb
Classifier: Intended Audience :: Developers
Classifier: Programming Language :: Python :: 3
Classifier: License :: OSI Approved :: MIT License
Classifier: Operating System :: Unix
Classifier: Operating System :: MacOS :: MacOS X
Classifier: Operating System :: Microsoft :: Windows
Classifier: Topic :: Scientific/Engineering :: Electronic Design Automation (EDA)
Requires-Python: >=3.6
License-File: LICENSE
Requires-Dist: cocotb>=1.8.0
Requires-Dist: wavedrom
Provides-Extra: test
Requires-Dist: pytest; extra == "test"
Requires-Dist: cocotbext-ahb; extra == "test"
